exengine/__init__.py
exengine/_version.py
exengine/base_classes.py
exengine/conftest.py
exengine/data.py
exengine/device_types.py
exengine/notifications.py
exengine/backends/__init__.py
exengine/backends/micromanager/README.md
exengine/backends/micromanager/__init__.py
exengine/backends/micromanager/mm_device_implementations.py
exengine/backends/micromanager/mm_utils.py
exengine/backends/micromanager/test/__init__.py
exengine/backends/micromanager/test/test_mm_camera.py
exengine/backends/micromanager/test/test_mm_properties.py
exengine/events/__init__.py
exengine/events/detector_events.py
exengine/events/misc_events.py
exengine/events/multi_d_events.py
exengine/events/positioner_events.py
exengine/events/property_events.py
exengine/events/test/__init__.py
exengine/events/test/test_multi_d_events_function.py
exengine/examples/implicit_vs_explicit_excutor.py
exengine/examples/micromanager_example.py
exengine/examples/using_devices.py
exengine/integration_tests/__init__.py
exengine/integration_tests/test_events_and_notifications.py
exengine/integration_tests/test_imports.py
exengine/integration_tests/test_preferred_thread_annotations.py
exengine/integration_tests/work_in_progress/__init__.py
exengine/integration_tests/work_in_progress/_test_multid_events_low_level.py
exengine/integration_tests/work_in_progress/continuous_capture_alternatives.py
exengine/kernel/__init__.py
exengine/kernel/data_coords.py
exengine/kernel/data_handler.py
exengine/kernel/data_storage_base.py
exengine/kernel/device.py
exengine/kernel/ex_event_base.py
exengine/kernel/ex_event_capabilities.py
exengine/kernel/ex_future.py
exengine/kernel/executor.py
exengine/kernel/notification_base.py
exengine/kernel/threading_decorator.py
exengine/kernel/test/__init__.py
exengine/kernel/test/test_data_coords.py
exengine/kernel/test/test_data_handler.py
exengine/kernel/test/test_device.py
exengine/kernel/test/test_executor.py
exengine/kernel/test/test_futures.py
exengine/kernel/test/test_notifications.py
exengine-0.4.0.dist-info/licenses/LICENSE
exengine-0.4.0.dist-info/WHEEL
exengine-0.4.0.dist-info/METADATA
exengine-0.4.0.dist-info/RECORD
