Metadata-Version: 2.4
Name: exengine
Version: 0.4.0
Summary: Microscopy execution engine with support for multiple hardware backends
Author-email: Henry Pinkard <henry.pinkard.open.source@gmail.com>
Classifier: License :: OSI Approved :: BSD License
Classifier: Operating System :: OS Independent
License-File: LICENSE
Requires-Dist: pydantic
Requires-Dist: numpy
Requires-Dist: mmpycorex ; extra == "all"
Requires-Dist: ndstorage ; extra == "all"
Requires-Dist: sphinx ; extra == "docs"
Requires-Dist: mmpycorex ; extra == "micromanager"
Requires-Dist: ndstorage ; extra == "ndstorage"
Requires-Dist: pytest ; extra == "test"
Project-URL: Home, https://github.com/micro-manager/ExEngine
Provides-Extra: all
Provides-Extra: docs
Provides-Extra: micromanager
Provides-Extra: ndstorage
Provides-Extra: test
